modnn/Config.py
modnn/Dataset.py
modnn/Play.py
modnn/__init__.py
modnn/hyper_tune.py
modnn/run.py
modnn/utils.py
modnn/Models/BaseNN.py
modnn/Models/ModNN_data.py
modnn/Models/ModNN_phy.py
modnn/Models/PolicyNN.py
modnn/Models/__init__.py
modnn-3.0.9.dist-info/licenses/LICENSE
modnn-3.0.9.dist-info/METADATA
modnn-3.0.9.dist-info/WHEEL
modnn-3.0.9.dist-info/top_level.txt
modnn-3.0.9.dist-info/RECORD
