Metadata-Version: 2.4
Name: modnn
Version: 3.0.9
Summary: Physics-Informed Modularized Neural Network for Building Energy Modeling
Author-email: Zixin Jiang <zjiang19@syr.edu>
License-Expression: MIT
Requires-Python: >=3.7
License-File: LICENSE
Requires-Dist: numpy
Requires-Dist: torch
Requires-Dist: pandas
Requires-Dist: matplotlib
Requires-Dist: seaborn
Requires-Dist: scikit-learn
Requires-Dist: tqdm
Dynamic: license-file
